LICENSE
MANIFEST.in
README.md
setup.cfg
setup.py
crawl_image/__init__.py
crawl_image/index.py
crawl_image/run_factory.py
crawl_image.egg-info/PKG-INFO
crawl_image.egg-info/SOURCES.txt
crawl_image.egg-info/dependency_links.txt
crawl_image.egg-info/requires.txt
crawl_image.egg-info/top_level.txt
crawl_image/__pycache__/__init__.cpython-36.pyc
crawl_image/__pycache__/index.cpython-36.pyc
crawl_image/__pycache__/run_factory.cpython-36.pyc
crawl_image/config/__init__.py
crawl_image/config/setting.py
crawl_image/config/__pycache__/__init__.cpython-36.pyc
crawl_image/config/__pycache__/setting.cpython-36.pyc
crawl_image/model/__init__.py
crawl_image/model/model.py
crawl_image/model/__pycache__/__init__.cpython-36.pyc
crawl_image/model/__pycache__/model.cpython-36.pyc