Metadata-Version: 1.1
Name: crawl-image
Version: 0.1.0
Summary: fast crawl web image source or image url list file
Home-page: https://github.com/xiaohong2019/crawl_image
Author: xiaohong2019
Author-email: 2229009854@qq.com
License: UNKNOWN
Platform: UNKNOWN
Classifier: Programming Language :: Python :: 3
Classifier: License :: OSI Approved :: MIT License
Classifier: Operating System :: OS Independent
